{"name":"Verify Score visibility when not reviewed","id":"mentee-task-page-task-bar;verify-score-visibility-when-not-reviewed","testSteps":[{"number":1,"description":"Given User want to login as Mentee","duration":10190,"startTime":"2022-11-14T01:08:06.505+07:00[Asia/Bangkok]","result":"IGNORED","precondition":false,"level":0},{"number":2,"description":"And User click nav option Task on Mentee Page","duration":1,"startTime":"2022-11-14T01:08:16.696+07:00[Asia/Bangkok]","result":"IGNORED","precondition":false,"level":0},{"number":3,"description":"When Task not scored","duration":1,"startTime":"2022-11-14T01:08:16.698+07:00[Asia/Bangkok]","result":"IGNORED","precondition":false,"level":0},{"number":4,"description":"Then User see score 0","duration":1,"startTime":"2022-11-14T01:08:16.699+07:00[Asia/Bangkok]","result":"IGNORED","precondition":false,"level":0}],"userStory":{"id":"mentee-task-page-task-bar","storyName":"Mentee Task Page Task Bar","displayName":"Mentee Task Page Task Bar","path":"menteeTaskPage/menteeTaskPageTaskBar.feature","type":"feature"},"featureTag":{"name":"Mentee task page/Mentee Task Page Task Bar","type":"feature","displayName":"Mentee task page/Mentee Task Page Task Bar"},"title":"Verify Score visibility when not reviewed","description":"","backgroundTitle":"User already in Mentee Task Page","backgroundDescription":"","tags":[{"name":"rerunbroken","type":"tag","displayName":"rerunbroken"},{"name":"rerubroken","type":"tag","displayName":"rerubroken"},{"name":"Mentee task page/Mentee Task Page Task Bar","type":"feature","displayName":"Mentee Task Page Task Bar"},{"name":"Passed","type":"Manual","displayName":"Passed"},{"name":"Manual","type":"tag","displayName":"Manual"},{"name":"Mentee task page","type":"capability","displayName":"Mentee task page"},{"name":"mentee-task","type":"tag","displayName":"mentee-task"}],"startTime":"2022-11-14T01:08:06.498+07:00[Asia/Bangkok]","duration":10203,"projectKey":"","annotatedResult":"SUCCESS","isManualTestingUpToDate":false,"manual":true,"testSource":"Cucumber","result":"SUCCESS"}