{"name":"Verify all text on page for spelling and grammatical errors","id":"login-page-visual-testing;verify-all-text-on-page-for-spelling-and-grammatical-errors","testSteps":[{"number":1,"description":"Given Tester already on Login Page","duration":1,"startTime":"2022-11-13T15:09:13.288+07:00[Asia/Bangkok]","result":"IGNORED","precondition":false,"level":0},{"number":2,"description":"When Tester check page spelling and grammatical error","duration":1,"startTime":"2022-11-13T15:09:13.290+07:00[Asia/Bangkok]","result":"IGNORED","precondition":false,"level":0},{"number":3,"description":"Then error is on acceptable level\"","duration":1,"startTime":"2022-11-13T15:09:13.292+07:00[Asia/Bangkok]","result":"IGNORED","precondition":false,"level":0}],"userStory":{"id":"login-page-visual-testing","storyName":"Login Page Visual Testing","displayName":"Login Page Visual Testing","path":"login/loginPageVisualTesting.feature","type":"feature"},"featureTag":{"name":"Login/Login Page Visual Testing","type":"feature","displayName":"Login/Login Page Visual Testing"},"title":"Verify all text on page for spelling and grammatical errors","description":"","tags":[{"name":"Login/Login Page Visual Testing","type":"feature","displayName":"Login Page Visual Testing"},{"name":"Passed","type":"Manual","displayName":"Passed"},{"name":"Manual","type":"tag","displayName":"Manual"},{"name":"login","type":"tag","displayName":"login"},{"name":"Login","type":"capability","displayName":"Login"}],"startTime":"2022-11-13T15:09:13.282+07:00[Asia/Bangkok]","duration":12,"projectKey":"","annotatedResult":"SUCCESS","isManualTestingUpToDate":false,"manual":true,"testSource":"Cucumber","result":"SUCCESS"}