{"name":"Verify application crash handling method and should be redirected to error page","id":"login-page-visual-testing;verify-application-crash-handling-method-and-should-be-redirected-to-error-page","testSteps":[{"number":1,"description":"Given Tester already on Login Page","duration":2,"startTime":"2022-11-13T15:09:13.247+07:00[Asia/Bangkok]","result":"SKIPPED","precondition":false,"level":0},{"number":2,"description":"When the app crash","duration":3,"startTime":"2022-11-13T15:09:13.252+07:00[Asia/Bangkok]","result":"SKIPPED","precondition":false,"level":0},{"number":3,"description":"Then Page crash handling is displayed\"","duration":4,"startTime":"2022-11-13T15:09:13.257+07:00[Asia/Bangkok]","result":"SKIPPED","precondition":false,"level":0}],"userStory":{"id":"login-page-visual-testing","storyName":"Login Page Visual Testing","displayName":"Login Page Visual Testing","path":"login/loginPageVisualTesting.feature","type":"feature"},"featureTag":{"name":"Login/Login Page Visual Testing","type":"feature","displayName":"Login/Login Page Visual Testing"},"title":"Verify application crash handling method and should be redirected to error page","description":"","tags":[{"name":"Login/Login Page Visual Testing","type":"feature","displayName":"Login Page Visual Testing"},{"name":"Manual","type":"tag","displayName":"Manual"},{"name":"login","type":"tag","displayName":"login"},{"name":"Login","type":"capability","displayName":"Login"},{"name":"Failed","type":"Manual","displayName":"Failed"}],"startTime":"2022-11-13T15:09:13.236+07:00[Asia/Bangkok]","duration":29,"testFailureMessage":"Failing manual test","projectKey":"","annotatedResult":"FAILURE","isManualTestingUpToDate":false,"manual":true,"testSource":"Cucumber","result":"FAILURE"}