{"name":"Verify Delete User functionality","id":"admin-home-page-list-user;verify-delete-user-functionality","testSteps":[{"number":1,"description":"Given User want to login as Admin","duration":5330,"startTime":"2022-11-13T16:36:39.568+07:00[Asia/Bangkok]","result":"SUCCESS","precondition":false,"level":0},{"number":2,"description":"When User click Delete Button","duration":595,"startTime":"2022-11-13T16:36:44.900+07:00[Asia/Bangkok]","result":"SUCCESS","precondition":false,"level":0},{"number":3,"description":"And User click Yes, delete!","duration":368,"startTime":"2022-11-13T16:36:45.496+07:00[Asia/Bangkok]","result":"SUCCESS","precondition":false,"level":0},{"number":4,"description":"Then Message User Successfully Deleted appeared","duration":14,"startTime":"2022-11-13T16:36:45.866+07:00[Asia/Bangkok]","result":"SUCCESS","precondition":false,"level":0}],"userStory":{"id":"admin-home-page-list-user","storyName":"Admin Home Page List User","displayName":"Admin Home Page List User","path":"adminHomePage/adminHomePageListUser.feature","type":"feature"},"featureTag":{"name":"Admin home page/Admin Home Page List User","type":"feature","displayName":"Admin home page/Admin Home Page List User"},"title":"Verify Delete User functionality","description":"","backgroundTitle":"User already login as Admin","backgroundDescription":"","tags":[{"name":"admin-home","type":"tag","displayName":"admin-home"},{"name":"Admin home page/Admin Home Page List User","type":"feature","displayName":"Admin Home Page List User"},{"name":"Admin home page","type":"capability","displayName":"Admin home page"}],"startTime":"2022-11-13T16:36:39.562+07:00[Asia/Bangkok]","duration":6325,"projectKey":"","sessionId":"cea08b58-b47a-4800-ab02-77121aeb553d","driver":"firefox","isManualTestingUpToDate":false,"manual":false,"testSource":"Cucumber","result":"SUCCESS"}