{"name":"Verify email is unique value","id":"register-new-member;verify-email-is-unique-value","testSteps":[{"number":1,"description":"Given User want to login as Admin","duration":5272,"startTime":"2022-11-13T22:59:30.783+07:00[Asia/Bangkok]","result":"SUCCESS","precondition":false,"level":0},{"number":2,"description":"And User click nav option Member on Admin Page","duration":317,"startTime":"2022-11-13T22:59:36.058+07:00[Asia/Bangkok]","result":"SUCCESS","precondition":false,"level":0},{"number":3,"description":"When Admin register new member with already registered email","duration":1001,"startTime":"2022-11-13T22:59:36.376+07:00[Asia/Bangkok]","result":"SUCCESS","precondition":false,"level":0},{"number":4,"description":"Then Message Email already registered appeared","duration":2161,"startTime":"2022-11-13T22:59:37.379+07:00[Asia/Bangkok]","screenshots":[{"screenshot":"00161a728bbf0a5fc071ad2fdc04414b70a934d6e20941add26212a0b36783bd.png","htmlSource":"pagesource155189777578965171.html","timeStamp":1668355179539,"screenshotName":"00161a728bbf0a5fc071ad2fdc04414b70a934d6e20941add26212a0b36783bd.png"}],"exception":{"errorType":"org.opentest4j.AssertionFailedError","message":"expected: \u003ctrue\u003e but was: \u003cfalse\u003e","stackTrace":[{"declaringClass":"mentutor.Interactions.UserInteractions","methodName":"isMessageDisplayed","fileName":"UserInteractions.java","lineNumber":154},{"declaringClass":"mentutor.StepDefs.Login.LoginStepDefs","methodName":"messageAppeared","fileName":"LoginStepDefs.java","lineNumber":68},{"declaringClass":"✽","methodName":"Message Email already registered appeared","fileName":"file:///C:/Users/isyah/Desktop/CAPSTONE/Testing/QE-UI/src/test/resources/features/registerUser/registerNewUser.feature","lineNumber":124}]},"result":"FAILURE","precondition":false,"level":0}],"userStory":{"id":"register-new-member","storyName":"Register New Member","displayName":"Register New Member","path":"registerUser/registerNewUser.feature","narrative":"  As an Admin\n  I want to __Register New Member__\n  In order to **Create New User Credentials**","type":"feature"},"featureTag":{"name":"Register user/Register New Member","type":"feature","displayName":"Register user/Register New Member"},"title":"Verify email is unique value","description":"","backgroundTitle":"User already login as Admin","backgroundDescription":"","tags":[{"name":"rerunbroken","type":"tag","displayName":"rerunbroken"},{"name":"Register user","type":"capability","displayName":"Register user"},{"name":"Register user/Register New Member","type":"feature","displayName":"Register New Member"},{"name":"register","type":"tag","displayName":"register"}],"startTime":"2022-11-13T22:59:30.765+07:00[Asia/Bangkok]","duration":8778,"testFailureCause":{"errorType":"org.opentest4j.AssertionFailedError","message":"expected: \u003ctrue\u003e but was: \u003cfalse\u003e","stackTrace":[{"declaringClass":"mentutor.Interactions.UserInteractions","methodName":"isMessageDisplayed","fileName":"UserInteractions.java","lineNumber":154},{"declaringClass":"mentutor.StepDefs.Login.LoginStepDefs","methodName":"messageAppeared","fileName":"LoginStepDefs.java","lineNumber":68},{"declaringClass":"✽","methodName":"Message Email already registered appeared","fileName":"file:///C:/Users/isyah/Desktop/CAPSTONE/Testing/QE-UI/src/test/resources/features/registerUser/registerNewUser.feature","lineNumber":124}]},"testFailureClassname":"org.opentest4j.AssertionFailedError","testFailureMessage":"expected: \u003ctrue\u003e but was: \u003cfalse\u003e","testFailureSummary":"FAILURE;org.opentest4j.AssertionFailedError;expected: \u003ctrue\u003e but was: \u003cfalse\u003e;UserInteractions.java","projectKey":"","annotatedResult":"FAILURE","sessionId":"d9df4b62-35c4-4d1c-8b7d-9123fd466e2f","driver":"firefox","isManualTestingUpToDate":false,"manual":false,"testSource":"Cucumber","result":"FAILURE"}